<?xml version="1.0" encoding="UTF-8"?>
<SimulationData xsi:noNamespaceSchemaLocation="../schemas/simulation.xsd" xmlns:xsi="http://www.w3.org/2001/XMLSchema-instance">
<SimulationProfile>
		<StartTime></StartTime>
		<EndTime></EndTime>
		<TokensInBundle>100</TokensInBundle>
		<TotalTokens>1000</TotalTokens>
		<CostPerToken>1</CostPerToken>
		<Resources>
			<Resource>
				<TODO></TODO>
			</Resource>
		</Resources>
	</SimulationProfile>	
	<Tasks>
		<Task>
			<Id>8</Id>
			<ResourceWaitTime>100</ResourceWaitTime>
			<ProcessingTime>200</ProcessingTime>
		</Task>
	</Tasks>
	<Gateways>
		<Gateway>
			<Id>9</Id>
			<GateRefs>
				<GateRef>
					<IdRef>6</IdRef>
					<Probability>90</Probability>
				</GateRef>
				<GateRef>
					<IdRef>8</IdRef>
					<Probability>10</Probability>
				</GateRef>
			</GateRefs>
		</Gateway>
	</Gateways>
	
</SimulationData>
